refactor/__init__.py
refactor/logging/__init__.py
refactor/logging/stdout.py
refactor/objects/__init__.py
refactor/objects/object.py
refactor/objects/serializers.py
refactor/patterns/__init__.py
refactor/patterns/creational/__init__.py
refactor/patterns/creational/singleton.py
refactor/resources/__init__.py
refactor/resources/loaders.py
refactor/resources/resources.py
pyrefactoring-0.0.1.1.post10.dist-info/LICENSE
pyrefactoring-0.0.1.1.post10.dist-info/METADATA
pyrefactoring-0.0.1.1.post10.dist-info/WHEEL
pyrefactoring-0.0.1.1.post10.dist-info/top_level.txt
pyrefactoring-0.0.1.1.post10.dist-info/zip-safe
pyrefactoring-0.0.1.1.post10.dist-info/RECORD
